[{"persoonlijk": "37.50", "indexscore": "23.00", "naam": "Peter", "gewonnen": "3", "gespeeld": "8", "absoluut": "37.50"}, {"persoonlijk": "14.29", "indexscore": "-16.13", "naam": "Marijn", "gewonnen": "1", "gespeeld": "7", "absoluut": "12.50"}, {"persoonlijk": "0.00", "indexscore": "-11.63", "naam": "Rik", "gewonnen": "0", "gespeeld": "4", "absoluut": "0.00"}, {"persoonlijk": "12.50", "indexscore": "-2.63", "naam": "Martijn", "gewonnen": "1", "gespeeld": "8", "absoluut": "12.50"}, {"persoonlijk": "14.29", "indexscore": "17.00", "naam": "Paul", "gewonnen": "1", "gespeeld": "7", "absoluut": "12.50"}, {"persoonlijk": "66.67", "indexscore": "27.38", "naam": "Jasper", "gewonnen": "2", "gespeeld": "3", "absoluut": "25.00"}]